{
  "date": "2026-04-08",
  "category": "wine",
  "article_count": 64,
  "source_count": 12,
  "matched_count": 21,
  "top_entities": [
    {
      "name": "region",
      "count": 63
    },
    {
      "name": "grape_variety",
      "count": 44
    },
    {
      "name": "climate_zone",
      "count": 24
    },
    {
      "name": "winery",
      "count": 20
    }
  ],
  "sources": {
    "Wine21": 10,
    "Wine Industry Advisor": 12,
    "Sonoma Magazine": 2,
    "Federdoc": 10,
    "Wine Enthusiast": 4,
    "Gambero Rosso": 7,
    "Decanter": 1,
    "Vino Joy News": 5,
    "Wine Dharma": 4,
    "The Drinks Business": 6,
    "Enolife": 2,
    "Wine Magazine South Africa": 1
  },
  "generated_at": "2026-04-08T09:36:24.075581+09:00"
}