{
  "run_date": "2026-06-21",
  "run_timestamp": "2026-06-21T00:06:08.941907+00:00",
  "collection": {
    "sources_active": 42,
    "sources_attempted": 42,
    "sources_succeeded": 39,
    "sources_failed": 3,
    "success_rate": "92.9%"
  },
  "articles": {
    "collected": 385,
    "new": 385,
    "duplicate": 0
  },
  "entities": {
    "extracted": 1960
  },
  "report": {
    "generated": true,
    "cards": 64,
    "sections": 0
  },
  "top_source": {
    "name": "Wine Industry Advisor",
    "count": 245,
    "percentage": 13.9
  },
  "runtime_seconds": 67.86135959625244,
  "errors": [
    "Wine Review Korea RSS: RSSCollector: No items collected",
    "1 Wine Dude: RSSCollector: 403 Client Error: Forbidden for url: https://www.1winedude.com/feed/",
    "Wine Review Online: RSSCollector: 403 Client Error: Forbidden for url: https://winereviewonline.com/feed/"
  ],
  "notes": null
}